matrix_field/__init__.py
matrix_field/fields.py
matrix_field/forms.py
matrix_field/models.py
matrix_field/test_settings.py
matrix_field/tests.py
matrix_field/validators.py
django_matrix_field-0.3.dist-info/METADATA
django_matrix_field-0.3.dist-info/WHEEL
django_matrix_field-0.3.dist-info/top_level.txt
django_matrix_field-0.3.dist-info/RECORD
