Metadata-Version: 2.1
Name: django-matrix-field
Version: 0.3
Summary: A Django app providing database and form fields for matrices (arrays of arrays).
Home-page: http://github.com/mfogel/django-matrix-field/
Author: Mike Fogel
Author-email: mike@fogel.ca
License: BSD
Classifier: Development Status :: 4 - Beta
Classifier: Environment :: Web Environment
Classifier: Intended Audience :: Developers
Classifier: License :: OSI Approved :: BSD License
Classifier: Operating System :: OS Independent
Classifier: Programming Language :: Python
Classifier: Topic :: Utilities
Classifier: Framework :: Django
Requires-Dist: django
